badabump/__init__.py
badabump/__main__.py
badabump/annotations.py
badabump/changelog.py
badabump/ci/__init__.py
badabump/ci/__main__.py
badabump/ci/py.typed
badabump/cleaners.py
badabump/cli/__init__.py
badabump/cli/app.py
badabump/cli/arguments.py
badabump/cli/ci_app.py
badabump/cli/commands.py
badabump/cli/output.py
badabump/cli/py.typed
badabump/configs.py
badabump/constants.py
badabump/enums.py
badabump/exceptions.py
badabump/git.py
badabump/loaders.py
badabump/py.typed
badabump/regexps.py
badabump/versions/__init__.py
badabump/versions/calver.py
badabump/versions/exceptions.py
badabump/versions/formatting.py
badabump/versions/parsing.py
badabump/versions/pre_release.py
badabump/versions/py.typed
badabump/versions/semver.py
badabump/versions/version.py
badabump-22.1.0.dist-info/entry_points.txt
badabump-22.1.0.dist-info/METADATA
badabump-22.1.0.dist-info/LICENSE
badabump-22.1.0.dist-info/WHEEL
badabump-22.1.0.dist-info/RECORD
