Metadata-Version: 2.1
Name: badabump
Version: 22.1.0
Summary: Manage changelog and bump project version number using conventional commits from latest git tag. Support Python & JavaScript projects and CalVer & SemVer schemas. Designed to run at GitHub Actions.
Home-page: https://igordavydenko.com/projects/#badabump
License: BSD-3-Clause
Keywords: changelog,conventional commit,bump,version,calver,semver,pre release
Author: Igor Davydenko
Author-email: iam@igordavydenko.com
Requires-Python: >=3.7,<4.0
Classifier: Development Status :: 5 - Production/Stable
Classifier: Environment :: Console
Classifier: Intended Audience :: Developers
Classifier: Intended Audience :: System Administrators
Classifier: License :: OSI Approved :: BSD License
Classifier: Operating System :: OS Independent
Classifier: Programming Language :: Python :: 3
Classifier: Programming Language :: Python :: 3.7
Classifier: Programming Language :: Python :: 3.8
Classifier: Programming Language :: Python :: 3.9
Classifier: Programming Language :: Python :: 3.10
Classifier: Programming Language :: Python :: 3.11
Classifier: Programming Language :: Python :: 3 :: Only
Classifier: Topic :: Software Development
Classifier: Topic :: Utilities
Classifier: Typing :: Typed
Requires-Dist: attrs (>=22.1.0,<23.0.0)
Requires-Dist: tomli (>=1.2.0,<3) ; python_full_version <= "3.11.0a6"
Project-URL: Bug Tracker, https://github.com/playpauseandstop/badabump/issues
Project-URL: Repository, https://github.com/playpauseandstop/badabump
